[
  {
    "sku": "SW-015",
    "name": "Zelda: Skyward Sword HD",
    "reason": "No image found in article"
  },
  {
    "sku": "SW-019",
    "name": "Mario Kart 8 Deluxe",
    "reason": "No image found in article"
  },
  {
    "sku": "SW-021",
    "name": "New Super Mario Bros. U Deluxe",
    "reason": "No image found in article"
  },
  {
    "sku": "SW-022",
    "name": "Super Mario 3D World + Bowser's Fury",
    "reason": "No image found in article"
  },
  {
    "sku": "SW-025",
    "name": "Super Mario RPG",
    "reason": "No image found in article"
  },
  {
    "sku": "SW-046",
    "name": "Pikmin 3 Deluxe",
    "reason": "No image found in article"
  },
  {
    "sku": "SW-048",
    "name": "Xenoblade Chronicles: Definitive Edition",
    "reason": "No image found in article"
  },
  {
    "sku": "SW-079",
    "name": "Undertale",
    "reason": "URL not found for: Undertale vector logo on black borders.svg"
  },
  {
    "sku": "SW-097",
    "name": "Overcooked! All You Can Eat",
    "reason": "No image found in article"
  },
  {
    "sku": "SW-106",
    "name": "Collection of Mana",
    "reason": "No image found in article"
  },
  {
    "sku": "SW-108",
    "name": "Borderlands Legendary Collection",
    "reason": "No image found in article"
  },
  {
    "sku": "SW-109",
    "name": "Naruto Storm Trilogy",
    "reason": "No image found in article"
  },
  {
    "sku": "SW-113",
    "name": "Pikmin 1+2",
    "reason": "No image found in article"
  },
  {
    "sku": "3DS-016",
    "name": "Luigi's Mansion 2",
    "reason": "No article mapping"
  },
  {
    "sku": "3DS-023",
    "name": "DK Country Returns 3D",
    "reason": "No image found in article"
  },
  {
    "sku": "GB-001",
    "name": "Pokémon Red",
    "reason": "No image found in article"
  },
  {
    "sku": "GB-002",
    "name": "Pokémon Blue",
    "reason": "No image found in article"
  },
  {
    "sku": "GB-003",
    "name": "Pokémon Yellow",
    "reason": "No image found in article"
  },
  {
    "sku": "GB-005",
    "name": "Pokémon Silver",
    "reason": "URL not found for: Pokémon Gold and Silver.jpg"
  },
  {
    "sku": "GB-016",
    "name": "Donkey Kong",
    "reason": "No article mapping"
  },
  {
    "sku": "GBA-007",
    "name": "Zelda: ALttP / Four Swords",
    "reason": "No image found in article"
  },
  {
    "sku": "N64-009",
    "name": "GoldenEye 007",
    "reason": "No image found in article"
  },
  {
    "sku": "N64-011",
    "name": "Banjo-Kazooie",
    "reason": "URL not found for: Banjo Kazooie logo.png"
  },
  {
    "sku": "SNES-007",
    "name": "Donkey Kong Country 2",
    "reason": "No image found in article"
  },
  {
    "sku": "SNES-008",
    "name": "Donkey Kong Country 3",
    "reason": "No image found in article"
  },
  {
    "sku": "WII-013",
    "name": "DK Country Returns",
    "reason": "No article mapping"
  },
  {
    "sku": "WII-017",
    "name": "Metroid Prime 3",
    "reason": "No article mapping"
  },
  {
    "sku": "WIIU-002",
    "name": "Zelda: Wind Waker HD",
    "reason": "No image found in article"
  },
  {
    "sku": "WIIU-003",
    "name": "Zelda: Twilight Princess HD",
    "reason": "No image found in article"
  },
  {
    "sku": "WIIU-007",
    "name": "Splatoon",
    "reason": "URL not found for: Splatoon Logo transparent.svg"
  }
]