[
  {"file": "Foto 12-02-2026, 04 16 24.jpg", "side": "front", "game": "The Legend of Zelda: The Wind Waker HD", "platform": "Wii U", "sku": "WIIU-006"},
  {"file": "Foto 12-02-2026, 04 16 29.jpg", "side": "back", "game": "The Legend of Zelda: The Wind Waker HD", "platform": "Wii U", "sku": "WIIU-006"},
  {"file": "Foto 12-02-2026, 04 16 41.jpg", "side": "front", "game": "Mario Party 10", "platform": "Wii U", "sku": "WIIU-013"},
  {"file": "Foto 12-02-2026, 04 16 45.jpg", "side": "back", "game": "Mario Party 10", "platform": "Wii U", "sku": "WIIU-013"},
  {"file": "Foto 12-02-2026, 04 16 54.jpg", "side": "front", "game": "Wii Party U", "platform": "Wii U", "sku": "WIIU-021", "notes": "First copy"},
  {"file": "Foto 12-02-2026, 04 16 58.jpg", "side": "back", "game": "Wii Party U", "platform": "Wii U", "sku": "WIIU-021", "notes": "First copy"},
  {"file": "Foto 12-02-2026, 04 17 06.jpg", "side": "front", "game": "Pokken Tournament", "platform": "Wii U", "sku": "WIIU-022", "notes": "Has recycling sticker and price tag (10.00 GBP)"},
  {"file": "Foto 12-02-2026, 04 17 11.jpg", "side": "back", "game": "Pokken Tournament", "platform": "Wii U", "sku": "WIIU-022"},
  {"file": "Foto 12-02-2026, 04 17 31.jpg", "side": "front", "game": "Mario & Sonic at the Sochi 2014 Olympic Winter Games", "platform": "Wii U", "sku": "WIIU-023"},
  {"file": "Foto 12-02-2026, 04 17 34.jpg", "side": "back", "game": "Mario & Sonic at the Sochi 2014 Olympic Winter Games", "platform": "Wii U", "sku": "WIIU-023"},
  {"file": "Foto 12-02-2026, 04 17 43.jpg", "side": "front", "game": "LEGO Jurassic World", "platform": "Wii U", "sku": "WIIU-024"},
  {"file": "Foto 12-02-2026, 04 17 50.jpg", "side": "back", "game": "LEGO Jurassic World", "platform": "Wii U", "sku": "WIIU-024"},
  {"file": "Foto 12-02-2026, 04 17 59.jpg", "side": "front", "game": "Just Dance 2014", "platform": "Wii U", "sku": "WIIU-025"},
  {"file": "Foto 12-02-2026, 04 18 07.jpg", "side": "back", "game": "Just Dance 2014", "platform": "Wii U", "sku": "WIIU-025"},
  {"file": "Foto 12-02-2026, 04 18 20.jpg", "side": "front", "game": "Nintendo Land", "platform": "Wii U", "sku": "WIIU-026"},
  {"file": "Foto 12-02-2026, 04 18 27.jpg", "side": "back", "game": "Nintendo Land", "platform": "Wii U", "sku": "WIIU-026"},
  {"file": "Foto 12-02-2026, 04 18 37.jpg", "side": "front", "game": "Minecraft: Wii U Edition", "platform": "Wii U", "sku": "WIIU-027", "notes": "Bevat Super Mario Mash-Up"},
  {"file": "Foto 12-02-2026, 04 18 43.jpg", "side": "back", "game": "Minecraft: Wii U Edition", "platform": "Wii U", "sku": "WIIU-027"},
  {"file": "Foto 12-02-2026, 04 18 55.jpg", "side": "front", "game": "Wii Party U", "platform": "Wii U", "sku": "WIIU-021", "notes": "Second copy"},
  {"file": "Foto 12-02-2026, 04 19 00.jpg", "side": "back", "game": "Wii Party U", "platform": "Wii U", "sku": "WIIU-021", "notes": "Second copy"},
  {"file": "Foto 12-02-2026, 04 19 09.jpg", "side": "front", "game": "Mario Kart 8", "platform": "Wii U", "sku": "WIIU-001"},
  {"file": "Foto 12-02-2026, 04 19 14.jpg", "side": "back", "game": "Mario Kart 8", "platform": "Wii U", "sku": "WIIU-001"},
  {"file": "Foto 12-02-2026, 04 20 46.jpg", "side": "front", "game": "Sonic Lost World", "platform": "Wii U", "sku": "WIIU-028", "notes": "Deadly Six Editie"},
  {"file": "Foto 12-02-2026, 04 20 49.jpg", "side": "back", "game": "Sonic Lost World", "platform": "Wii U", "sku": "WIIU-028"},
  {"file": "Foto 12-02-2026, 04 20 56.jpg", "side": "front", "game": "New Super Mario Bros. Wii", "platform": "Wii", "sku": "WII-007"},
  {"file": "Foto 12-02-2026, 04 21 01.jpg", "side": "back", "game": "New Super Mario Bros. Wii", "platform": "Wii", "sku": "WII-007"},
  {"file": "Foto 12-02-2026, 04 21 08.jpg", "side": "front", "game": "Super Mario Galaxy 2", "platform": "Wii", "sku": "WII-004", "notes": "Has Preowned price sticker (19.99 GBP)"},
  {"file": "Foto 12-02-2026, 04 21 12.jpg", "side": "back", "game": "Super Mario Galaxy 2", "platform": "Wii", "sku": "WII-004"},
  {"file": "Foto 12-02-2026, 04 21 19.jpg", "side": "front", "game": "Mario Party 8", "platform": "Wii", "sku": "WII-011"},
  {"file": "Foto 12-02-2026, 04 21 22.jpg", "side": "back", "game": "Mario Party 8", "platform": "Wii", "sku": "WII-011"},
  {"file": "Foto 12-02-2026, 04 21 31.jpg", "side": "front", "game": "Sonic and the Secret Rings", "platform": "Wii", "sku": "WII-031"},
  {"file": "Foto 12-02-2026, 04 21 35.jpg", "side": "back", "game": "Sonic and the Secret Rings", "platform": "Wii", "sku": "WII-031"},
  {"file": "Foto 12-02-2026, 04 21 41.jpg", "side": "front", "game": "Wii Sports", "platform": "Wii", "sku": "WII-009", "notes": "Niet voor losse verkoop edition"},
  {"file": "Foto 12-02-2026, 04 21 49.jpg", "side": "back", "game": "Wii Sports", "platform": "Wii", "sku": "WII-009"},
  {"file": "Foto 12-02-2026, 04 21 56.jpg", "side": "front", "game": "Sonic Unleashed", "platform": "Wii", "sku": "WII-032"},
  {"file": "Foto 12-02-2026, 04 22 00.jpg", "side": "back", "game": "Sonic Unleashed", "platform": "Wii", "sku": "WII-032"},
  {"file": "Foto 12-02-2026, 04 22 06.jpg", "side": "front", "game": "The Legend of Zelda: The Wind Waker HD (Nintendo Selects)", "platform": "Wii U", "sku": "WIIU-029"},
  {"file": "Foto 12-02-2026, 04 22 10.jpg", "side": "back", "game": "The Legend of Zelda: The Wind Waker HD (Nintendo Selects)", "platform": "Wii U", "sku": "WIIU-029"},
  {"file": "Foto 12-02-2026, 04 22 16.jpg", "side": "front", "game": "Mario Strikers Charged Football", "platform": "Wii", "sku": "WII-019"},
  {"file": "Foto 12-02-2026, 04 22 21.jpg", "side": "back", "game": "Mario Strikers Charged Football", "platform": "Wii", "sku": "WII-019"},
  {"file": "Foto 12-02-2026, 04 22 27.jpg", "side": "front", "game": "Skylanders Imaginators", "platform": "Wii U", "sku": "WIIU-030"},
  {"file": "Foto 12-02-2026, 04 22 38.jpg", "side": "back", "game": "Skylanders Imaginators", "platform": "Wii U", "sku": "WIIU-030"},
  {"file": "Foto 12-02-2026, 04 22 49.jpg", "side": "front", "game": "Captain Toad: Treasure Tracker", "platform": "Wii U", "sku": "WIIU-016"},
  {"file": "Foto 12-02-2026, 04 22 52.jpg", "side": "back", "game": "Captain Toad: Treasure Tracker", "platform": "Wii U", "sku": "WIIU-016"},
  {"file": "Foto 12-02-2026, 04 22 58.jpg", "side": "front", "game": "New Super Mario Bros. Wii (Nintendo Selects)", "platform": "Wii", "sku": "WII-033"},
  {"file": "Foto 12-02-2026, 04 23 02.jpg", "side": "back", "game": "New Super Mario Bros. Wii (Nintendo Selects)", "platform": "Wii", "sku": "WII-033"},
  {"file": "Foto 12-02-2026, 04 23 07.jpg", "side": "front", "game": "Donkey Kong Country Returns", "platform": "Wii", "sku": "WII-008"},
  {"file": "Foto 12-02-2026, 04 23 11.jpg", "side": "back", "game": "Donkey Kong Country Returns", "platform": "Wii", "sku": "WII-008"},
  {"file": "Foto 12-02-2026, 04 23 16.jpg", "side": "front", "game": "LEGO Batman 3: Beyond Gotham", "platform": "Wii U", "sku": "WIIU-031"},
  {"file": "Foto 12-02-2026, 04 23 20.jpg", "side": "back", "game": "LEGO Batman 3: Beyond Gotham", "platform": "Wii U", "sku": "WIIU-031"},
  {"file": "Foto 12-02-2026, 04 23 25.jpg", "side": "front", "game": "The Legend of Zelda: Twilight Princess HD", "platform": "Wii U", "sku": "WIIU-007", "notes": "Has price sticker (44.99 EUR)"},
  {"file": "Foto 12-02-2026, 04 23 29.jpg", "side": "back", "game": "The Legend of Zelda: Twilight Princess HD", "platform": "Wii U", "sku": "WIIU-007"},
  {"file": "Foto 12-02-2026, 04 23 35.jpg", "side": "front", "game": "Just Dance 2017", "platform": "Wii U", "sku": "WIIU-032"},
  {"file": "Foto 12-02-2026, 04 23 38.jpg", "side": "back", "game": "Just Dance 2017", "platform": "Wii U", "sku": "WIIU-032"},
  {"file": "Foto 12-02-2026, 04 23 44.jpg", "side": "front", "game": "New Super Mario Bros. U + New Super Luigi U", "platform": "Wii U", "sku": "WIIU-008"},
  {"file": "Foto 12-02-2026, 04 23 48.jpg", "side": "back", "game": "New Super Mario Bros. U + New Super Luigi U", "platform": "Wii U", "sku": "WIIU-008"},
  {"file": "Foto 12-02-2026, 04 23 57.jpg", "side": "front", "game": "Mario & Sonic at the Rio 2016 Olympic Games", "platform": "Wii U", "sku": "WIIU-033"},
  {"file": "Foto 12-02-2026, 04 24 03.jpg", "side": "back", "game": "Mario & Sonic at the Rio 2016 Olympic Games", "platform": "Wii U", "sku": "WIIU-033"},
  {"file": "Foto 12-02-2026, 04 24 10.jpg", "side": "front", "game": "Paper Mario: Color Splash", "platform": "Wii U", "sku": "WIIU-018"},
  {"file": "Foto 12-02-2026, 04 24 15.jpg", "side": "back", "game": "Paper Mario: Color Splash", "platform": "Wii U", "sku": "WIIU-018"},
  {"file": "Foto 12-02-2026, 04 24 21.jpg", "side": "front", "game": "Wii Party", "platform": "Wii", "sku": "WII-034"},
  {"file": "Foto 12-02-2026, 04 24 25.jpg", "side": "back", "game": "Wii Party", "platform": "Wii", "sku": "WII-034"},
  {"file": "Foto 12-02-2026, 04 24 34.jpg", "side": "front", "game": "Wario Land: The Shake Dimension", "platform": "Wii", "sku": "WII-035"},
  {"file": "Foto 12-02-2026, 04 24 38.jpg", "side": "back", "game": "Wario Land: The Shake Dimension", "platform": "Wii", "sku": "WII-035"},
  {"file": "Foto 12-02-2026, 04 24 51.jpg", "side": "front", "game": "Splatoon", "platform": "Wii U", "sku": "WIIU-004"},
  {"file": "Foto 12-02-2026, 04 24 58.jpg", "side": "back", "game": "Splatoon", "platform": "Wii U", "sku": "WIIU-004"},
  {"file": "Foto 12-02-2026, 04 25 04.jpg", "side": "front", "game": "LEGO Dimensions", "platform": "Wii U", "sku": "WIIU-034"},
  {"file": "Foto 12-02-2026, 04 25 07.jpg", "side": "back", "game": "LEGO Dimensions", "platform": "Wii U", "sku": "WIIU-034"}
]
